nautobot_show_tech/__init__.py
nautobot_show_tech/api/__init__.py
nautobot_show_tech/helpers.py
nautobot_show_tech/jobs.py
nautobot_show_tech/management/commands/show_tech_check_apps.py
nautobot_show_tech/management/commands/show_tech_check_counts.py
nautobot_show_tech/management/commands/show_tech_check_django_settings.py
nautobot_show_tech/management/commands/show_tech_check_jobs.py
nautobot_show_tech/migrations/__init__.py
nautobot_show_tech/run_check.py
nautobot_show_tech/show_tech_checks/README.md
nautobot_show_tech/show_tech_checks/__init__.py
nautobot_show_tech/show_tech_checks/alias.yaml
nautobot_show_tech/show_tech_checks/ansible_version.yaml
nautobot_show_tech/show_tech_checks/available_commands.yaml
nautobot_show_tech/show_tech_checks/date.yaml
nautobot_show_tech/show_tech_checks/disk_space.yaml
nautobot_show_tech/show_tech_checks/dns.yaml
nautobot_show_tech/show_tech_checks/host_uptime.yaml
nautobot_show_tech/show_tech_checks/hostname.yaml
nautobot_show_tech/show_tech_checks/lscpu.yaml
nautobot_show_tech/show_tech_checks/meminfo.yaml
nautobot_show_tech/show_tech_checks/nautobot_server_apps.yaml
nautobot_show_tech/show_tech_checks/nautobot_server_counts.yaml
nautobot_show_tech/show_tech_checks/nautobot_server_django_settings.yaml
nautobot_show_tech/show_tech_checks/nautobot_server_health_check.yaml
nautobot_show_tech/show_tech_checks/nautobot_server_jobs.yaml
nautobot_show_tech/show_tech_checks/nautobot_server_version.yaml
nautobot_show_tech/show_tech_checks/os-release.yaml
nautobot_show_tech/show_tech_checks/pip_freeze.yaml
nautobot_show_tech/show_tech_checks/pip_version.yaml
nautobot_show_tech/show_tech_checks/pwd.yaml
nautobot_show_tech/show_tech_checks/python_version.yaml
nautobot_show_tech/show_tech_checks/subprocess_run.py
nautobot_show_tech/show_tech_checks/uname_a.yaml
nautobot_show_tech/show_tech_checks/which_pip.yaml
nautobot_show_tech/show_tech_checks/which_python.yaml
nautobot_show_tech/show_tech_checks/whoami.yaml
nautobot_show_tech-2.0.2.dist-info/LICENSE
nautobot_show_tech-2.0.2.dist-info/METADATA
nautobot_show_tech-2.0.2.dist-info/WHEEL
nautobot_show_tech-2.0.2.dist-info/entry_points.txt
nautobot_show_tech-2.0.2.dist-info/RECORD
