Metadata-Version: 2.1
Name: nautobot-show-tech
Version: 2.0.2
Summary: An app to aid in troubleshooting a Nautobot environment.
Home-page: https://github.com/networktocode-llc/nautobot-app-show-tech
License: Apache-2.0
Keywords: nautobot,nautobot-app,nautobot-plugin
Author: Network to Code, LLC
Author-email: info@networktocode.com
Requires-Python: >=3.8,<3.12
Classifier: Development Status :: 5 - Production/Stable
Classifier: Intended Audience :: Developers
Classifier: License :: OSI Approved :: Apache Software License
Classifier: Programming Language :: Python :: 3
Classifier: Programming Language :: Python :: 3.8
Classifier: Programming Language :: Python :: 3.9
Classifier: Programming Language :: Python :: 3.10
Classifier: Programming Language :: Python :: 3.11
Provides-Extra: all
Requires-Dist: click (>=8.1.0,<9.0.0)
Requires-Dist: nautobot (>=2.0.0,<3.0.0)
Requires-Dist: requests (>=2.31.0,<3.0.0)
Project-URL: Documentation, https://doshow-tech/en/latest/
Project-URL: Repository, https://github.com/networktocode-llc/nautobot-app-show-tech
